{"cameraMode":{"drawMode":0,"name":"Shaded","section":"Shading Mode"},"sceneLighting":true,"audioPlay":false,"sceneViewState":{"showFog":true,"showMaterialUpdate":false,"showSkybox":true,"showFlares":true,"showImageEffects":true,"showParticleSystems":true},"in2DMode":false,"pivot":{"x":-416.9255065917969,"y":6.623126029968262,"z":-473.4940185546875},"rotation":{"x":0.1287764012813568,"y":-0.6834766864776611,"z":0.12437210977077484,"w":0.707682192325592},"size":22.94732093811035,"orthographic":false}