{"cameraMode":{"drawMode":0,"name":"Shaded","section":"Shading Mode"},"sceneLighting":true,"audioPlay":false,"sceneViewState":{"showFog":true,"showMaterialUpdate":false,"showSkybox":true,"showFlares":true,"showImageEffects":true,"showParticleSystems":true},"in2DMode":false,"pivot":{"x":-303.6325988769531,"y":-188.85379028320313,"z":-37.171897888183597},"rotation":{"x":-0.18632365763187409,"y":0.7312403321266174,"z":-0.2204514592885971,"w":-0.6180428266525269},"size":203.3623504638672,"orthographic":false}